ifcraftcorpus/__init__.py
ifcraftcorpus/cli.py
ifcraftcorpus/embeddings.py
ifcraftcorpus/index.py
ifcraftcorpus/logging_utils.py
ifcraftcorpus/mcp_server.py
ifcraftcorpus/parser.py
ifcraftcorpus/providers.py
ifcraftcorpus/py.typed
ifcraftcorpus/search.py
ifcraftcorpus-1.5.0.data/data/share/ifcraftcorpus/corpus/agent-design/agent_memory_architecture.md
ifcraftcorpus-1.5.0.data/data/share/ifcraftcorpus/corpus/agent-design/agent_prompt_engineering.md
ifcraftcorpus-1.5.0.data/data/share/ifcraftcorpus/corpus/agent-design/multi_agent_patterns.md
ifcraftcorpus-1.5.0.data/data/share/ifcraftcorpus/corpus/audience-and-access/accessibility_guidelines.md
ifcraftcorpus-1.5.0.data/data/share/ifcraftcorpus/corpus/audience-and-access/audience_targeting.md
ifcraftcorpus-1.5.0.data/data/share/ifcraftcorpus/corpus/audience-and-access/localization_considerations.md
ifcraftcorpus-1.5.0.data/data/share/ifcraftcorpus/corpus/craft-foundations/audio_visual_integration.md
ifcraftcorpus-1.5.0.data/data/share/ifcraftcorpus/corpus/craft-foundations/collaborative_if_writing.md
ifcraftcorpus-1.5.0.data/data/share/ifcraftcorpus/corpus/craft-foundations/creative_workflow_pipeline.md
ifcraftcorpus-1.5.0.data/data/share/ifcraftcorpus/corpus/craft-foundations/diegetic_design.md
ifcraftcorpus-1.5.0.data/data/share/ifcraftcorpus/corpus/craft-foundations/idea_capture_and_hooks.md
ifcraftcorpus-1.5.0.data/data/share/ifcraftcorpus/corpus/craft-foundations/if_platform_tools.md
ifcraftcorpus-1.5.0.data/data/share/ifcraftcorpus/corpus/craft-foundations/player_analytics_metrics.md
ifcraftcorpus-1.5.0.data/data/share/ifcraftcorpus/corpus/craft-foundations/quality_standards_if.md
ifcraftcorpus-1.5.0.data/data/share/ifcraftcorpus/corpus/craft-foundations/research_and_verification.md
ifcraftcorpus-1.5.0.data/data/share/ifcraftcorpus/corpus/craft-foundations/testing_interactive_fiction.md
ifcraftcorpus-1.5.0.data/data/share/ifcraftcorpus/corpus/emotional-design/conflict_patterns.md
ifcraftcorpus-1.5.0.dist-info/METADATA
ifcraftcorpus-1.5.0.dist-info/WHEEL
ifcraftcorpus-1.5.0.dist-info/entry_points.txt
ifcraftcorpus-1.5.0.dist-info/licenses/LICENSE
ifcraftcorpus-1.5.0.dist-info/licenses/LICENSE-CONTENT
ifcraftcorpus-1.5.0.dist-info/RECORD
