Metadata-Version: 2.4
Name: ifcraftcorpus
Version: 1.5.0
Summary: Interactive fiction craft corpus with search library and MCP server
Project-URL: Homepage, https://pvliesdonk.github.io/if-craft-corpus
Project-URL: Repository, https://github.com/pvliesdonk/if-craft-corpus
Project-URL: Documentation, https://pvliesdonk.github.io/if-craft-corpus
Author: pvliesdonk
License: MIT
License-File: LICENSE
License-File: LICENSE-CONTENT
Keywords: corpus,craft,interactive-fiction,mcp,rag,search,writing
Classifier: Development Status :: 4 - Beta
Classifier: Intended Audience :: Developers
Classifier: License :: OSI Approved :: MIT License
Classifier: Programming Language :: Python :: 3
Classifier: Programming Language :: Python :: 3.10
Classifier: Programming Language :: Python :: 3.11
Classifier: Programming Language :: Python :: 3.12
Classifier: Topic :: Software Development :: Libraries :: Python Modules
Classifier: Topic :: Text Processing
Requires-Python: >=3.10
Requires-Dist: pyyaml>=6.0
Provides-Extra: all
Requires-Dist: fastmcp>=2.0; extra == 'all'
Requires-Dist: httpx>=0.25; extra == 'all'
Requires-Dist: numpy>=1.20; extra == 'all'
Provides-Extra: all-local
Requires-Dist: fastmcp>=2.0; extra == 'all-local'
Requires-Dist: numpy>=1.20; extra == 'all-local'
Requires-Dist: sentence-transformers>=2.0; extra == 'all-local'
Provides-Extra: dev
Requires-Dist: fastmcp>=2.0; extra == 'dev'
Requires-Dist: mypy>=1.0; extra == 'dev'
Requires-Dist: pre-commit>=3.0; extra == 'dev'
Requires-Dist: pytest-cov>=4.0; extra == 'dev'
Requires-Dist: pytest>=7.0; extra == 'dev'
Requires-Dist: python-semantic-release>=10.0; extra == 'dev'
Requires-Dist: ruff>=0.1; extra == 'dev'
Requires-Dist: types-pyyaml>=6.0; extra == 'dev'
Provides-Extra: docs
Requires-Dist: mkdocs-material>=9.0; extra == 'docs'
Requires-Dist: mkdocs>=1.5; extra == 'docs'
Provides-Extra: embeddings
Requires-Dist: numpy>=1.20; extra == 'embeddings'
Requires-Dist: sentence-transformers>=2.0; extra == 'embeddings'
Provides-Extra: embeddings-api
Requires-Dist: httpx>=0.25; extra == 'embeddings-api'
Requires-Dist: numpy>=1.20; extra == 'embeddings-api'
Provides-Extra: mcp
Requires-Dist: fastmcp>=2.0; extra == 'mcp'
